{"about.md":"CvQtcLXC","ai-creative-notes_index.md":"Cv82FrJI","ai-creative-notes_韩剧《富豪入赘我们村》剧本大纲.md":"D-pQEj9d","ai-tech-notes_github仓库清除历史提交记录方法.md":"CoGoIMDI","ai-tech-notes_index.md":"CtaACQhD","ai-tech-notes_javascript-typescript-批处理流程管理包推荐.md":"DBMSEo-u","ai-tech-notes_nginx上游连接错误日志分析.md":"Bsij_-xp","ai-tech-notes_npm包依赖管理最佳实践.md":"BOPCinnh","ai-tech-notes_pnpm workspace新建package规范流程.md":"BBzicLxz","ai-tech-notes_primevue package.json 配置详解.md":"k0GMMPpK","ai-tech-notes_primevue 构建系统完整指南.md":"CEc7Nbb2","ai-tech-notes_primevue 构建系统说明文档.md":"BObopJ8g","ai-tech-notes_typescript中type和interface的至关重要的区别.md":"Bpg_a0Sm","ai-tech-notes_typescript自动化测试方案建议（2025）.md":"BZm1q5lD","ai-tech-notes_为什么mongodb的用户评价不好.md":"B2gAep8s","ai-tech-notes_使用 indexeddb 和 service worker 动态加载前端代码.md":"BIGwkkgz","ai-tech-notes_如果某个高权限的团队成员把本地的 husky 卸载了，并且强制push了代码，远程仓库里的 husky 能防御吗？.md":"B7QhW9lq","ai-tech-notes_嵌套 git 仓库管理的最佳实践.md":"BVyL5xJa","ai-tech-notes_浏览器语音输入功能实现方法.md":"BGtP4Dat","index.md":"Cd558uko","list.md":"pWElAF2R"}
